CHANGES.rst
CONTRIBUTORS.rst
MANIFEST.in
README.rst
bootstrap.py
buildout.cfg
setup.py
test-4.0.x.cfg
test-4.1.x.cfg
test-4.2.x.cfg
src/collective/__init__.py
src/collective.request.player.egg-info/PKG-INFO
src/collective.request.player.egg-info/SOURCES.txt
src/collective.request.player.egg-info/dependency_links.txt
src/collective.request.player.egg-info/entry_points.txt
src/collective.request.player.egg-info/namespace_packages.txt
src/collective.request.player.egg-info/not-zip-safe
src/collective.request.player.egg-info/requires.txt
src/collective.request.player.egg-info/top_level.txt
src/collective/request/__init__.py
src/collective/request/player/__init__.py
src/collective/request/player/config.py
src/collective/request/player/configure.zcml
src/collective/request/player/interfaces.py
src/collective/request/player/testing.py
src/collective/request/player/testing.zcml
src/collective/request/player/utils.py
src/collective/request/player/browser/__init__.py
src/collective/request/player/browser/configure.zcml
src/collective/request/player/browser/views.py
src/collective/request/player/browser/resources/player.css
src/collective/request/player/browser/resources/player.png
src/collective/request/player/browser/templates/loader.pt
src/collective/request/player/browser/templates/player.pt
src/collective/request/player/profiles/default/browserlayer.xml
src/collective/request/player/profiles/default/controlpanel.xml
src/collective/request/player/profiles/default/cssregistry.xml
src/collective/request/player/profiles/default/metadata.xml
src/collective/request/player/profiles/testing/metadata.xml
src/collective/request/player/tests/__init__.py
src/collective/request/player/tests/test_setup.py
src/collective/request/player/tests/test_views.py
src/collective/request/player/tests/logs/create_page.json
src/collective/request/player/tests/logs/delete_folder.json
src/collective/request/player/tests/logs/welcom_page.json