Metadata-Version: 1.0
Name: collective.request.player
Version: 0.1.0b1
Summary: The package replays requests. It's a part of https://github.com/potar/dagger
Home-page: http://github.com/potar/collective.request.player
Author: Poburynnyi Taras (potar)
Author-email: poburynnyitaras@gmail.com
License: gpl
Keywords: request player
Platform: UNKNOWN
Classifier: Environment :: Web Environment
Classifier: Framework :: Plone
Classifier: Framework :: Plone :: 4.0
Classifier: Framework :: Plone :: 4.1
Classifier: Framework :: Plone :: 4.2
Classifier: Operating System :: OS Independent
Classifier: Programming Language :: Python
Classifier: Programming Language :: Python :: 2.6
Classifier: Topic :: Software Development :: Libraries :: Python Modules
